cohere/__init__.py
cohere/aliases.py
cohere/aws_client.py
cohere/base_client.py
cohere/bedrock_client.py
cohere/client.py
cohere/client_v2.py
cohere/config.py
cohere/connectors/__init__.py
cohere/connectors/client.py
cohere/connectors/raw_client.py
cohere/core/__init__.py
cohere/core/api_error.py
cohere/core/client_wrapper.py
cohere/core/datetime_utils.py
cohere/core/file.py
cohere/core/force_multipart.py
cohere/core/http_client.py
cohere/core/http_response.py
cohere/core/jsonable_encoder.py
cohere/core/pydantic_utilities.py
cohere/core/query_encoder.py
cohere/core/remove_none_from_dict.py
cohere/core/request_options.py
cohere/core/serialization.py
cohere/core/unchecked_base_model.py
cohere/datasets/__init__.py
cohere/datasets/client.py
cohere/datasets/raw_client.py
cohere/datasets/types/__init__.py
cohere/datasets/types/datasets_create_response.py
cohere/datasets/types/datasets_get_response.py
cohere/datasets/types/datasets_get_usage_response.py
cohere/datasets/types/datasets_list_response.py
cohere/embed_jobs/__init__.py
cohere/embed_jobs/client.py
cohere/embed_jobs/raw_client.py
cohere/embed_jobs/types/__init__.py
cohere/embed_jobs/types/create_embed_job_request_truncate.py
cohere/environment.py
cohere/errors/__init__.py
cohere/errors/bad_request_error.py
cohere/errors/client_closed_request_error.py
cohere/errors/forbidden_error.py
cohere/errors/gateway_timeout_error.py
cohere/errors/internal_server_error.py
cohere/errors/invalid_token_error.py
cohere/errors/not_found_error.py
cohere/errors/not_implemented_error.py
cohere/errors/service_unavailable_error.py
cohere/errors/too_many_requests_error.py
cohere/errors/unauthorized_error.py
cohere/errors/unprocessable_entity_error.py
cohere/finetuning/__init__.py
cohere/finetuning/client.py
cohere/finetuning/finetuning/__init__.py
cohere/finetuning/finetuning/types/__init__.py
cohere/finetuning/finetuning/types/base_model.py
cohere/finetuning/finetuning/types/base_type.py
cohere-5.16.0.dist-info/LICENSE
cohere-5.16.0.dist-info/METADATA
cohere-5.16.0.dist-info/WHEEL
cohere-5.16.0.dist-info/RECORD
