Metadata-Version: 2.1
Name: cohere
Version: 5.16.0
Summary: 
License: MIT
Requires-Python: >=3.9,<4.0
Classifier: Intended Audience :: Developers
Classifier: License :: OSI Approved :: MIT License
Classifier: Operating System :: MacOS
Classifier: Operating System :: Microsoft :: Windows
Classifier: Operating System :: OS Independent
Classifier: Operating System :: POSIX
Classifier: Operating System :: POSIX :: Linux
Classifier: Programming Language :: Python
Classifier: Programming Language :: Python :: 3
Classifier: Programming Language :: Python :: 3.9
Classifier: Programming Language :: Python :: 3.10
Classifier: Programming Language :: Python :: 3.11
Classifier: Programming Language :: Python :: 3.12
Classifier: Programming Language :: Python :: 3.8
Classifier: Topic :: Software Development :: Libraries :: Python Modules
Classifier: Typing :: Typed
Requires-Dist: fastavro (>=1.9.4,<2.0.0)
Requires-Dist: httpx (>=0.21.2)
Requires-Dist: httpx-sse (==0.4.0)
Requires-Dist: pydantic (>=1.9.2)
Requires-Dist: pydantic-core (>=2.18.2,<3.0.0)
Requires-Dist: requests (>=2.0.0,<3.0.0)
Requires-Dist: tokenizers (>=0.15,<1)
Requires-Dist: types-requests (>=2.0.0,<3.0.0)
Requires-Dist: typing_extensions (>=4.0.0)
